gpuheater/__init__.py
gpuheater/core.py
gpuheater-1.0.dist-info/LICENSE
gpuheater-1.0.dist-info/METADATA
gpuheater-1.0.dist-info/WHEEL
gpuheater-1.0.dist-info/dependency_links.txt
gpuheater-1.0.dist-info/entry_points.txt
gpuheater-1.0.dist-info/top_level.txt
gpuheater-1.0.dist-info/RECORD
