Metadata-Version: 2.1
Name: gpuheater
Version: 1.0
Summary: A Python package running full of GPUs for heating
Home-page: https://github.com/sword4869/gpuheater
Author: sword4869
License: MIT License
License-File: LICENSE
Requires-Dist: torch
Requires-Dist: argparse
Requires-Dist: nvitop
